devaudit/__init__.py
devaudit/cli.py
devaudit/auditors/__init__.py
devaudit/auditors/base.py
devaudit/auditors/docker_audit.py
devaudit/auditors/go_audit.py
devaudit/auditors/node_audit.py
devaudit/auditors/python_audit.py
devaudit/auditors/system_audit.py
devaudit/fixers/__init__.py
devaudit/fixers/docker_fix.py
devaudit/reporters/__init__.py
devaudit/reporters/console.py
devaudit/reporters/detailed.py
devaudit/reporters/summary.py
devaudit-0.1.0.dist-info/licenses/LICENSE
devaudit-0.1.0.dist-info/METADATA
devaudit-0.1.0.dist-info/WHEEL
devaudit-0.1.0.dist-info/entry_points.txt
devaudit-0.1.0.dist-info/top_level.txt
devaudit-0.1.0.dist-info/RECORD
