Metadata-Version: 2.4
Name: devaudit
Version: 0.1.0
Summary: Cross-platform developer environment auditing and cleanup tool
Home-page: https://github.com/aramantos/devaudit
Author: John Doyle
Author-email: john.doyle.mail@icloud.com
Project-URL: Bug Reports, https://github.com/aramantos/devaudit/issues
Project-URL: Source, https://github.com/aramantos/devaudit
Keywords: audit dependencies docker python nodejs developer-tools devops
Classifier: Development Status :: 3 - Alpha
Classifier: Intended Audience :: Developers
Classifier: Topic :: Software Development :: Build Tools
Classifier: Topic :: System :: Systems Administration
Classifier: License :: OSI Approved :: MIT License
Classifier: Programming Language :: Python :: 3
Classifier: Programming Language :: Python :: 3.8
Classifier: Programming Language :: Python :: 3.9
Classifier: Programming Language :: Python :: 3.10
Classifier: Programming Language :: Python :: 3.11
Classifier: Programming Language :: Python :: 3.12
Classifier: Operating System :: OS Independent
Requires-Python: >=3.8
License-File: LICENSE
Requires-Dist: rich>=13.7.0
Requires-Dist: click>=8.1.0
Dynamic: author
Dynamic: author-email
Dynamic: classifier
Dynamic: description
Dynamic: description-content-type
Dynamic: home-page
Dynamic: keywords
Dynamic: license-file
Dynamic: project-url
Dynamic: requires-dist
Dynamic: requires-python
Dynamic: summary
